reportsrender/__init__.py
reportsrender/cli.py
reportsrender/index.py
reportsrender/legacy.py
reportsrender/pandoc.py
reportsrender/papermill.py
reportsrender/rmd.py
reportsrender/util.py
reportsrender/templates/adaptive-bootstrap/.gitignore
reportsrender/templates/adaptive-bootstrap/LICENSE
reportsrender/templates/adaptive-bootstrap/README.md
reportsrender/templates/adaptive-bootstrap/index.html
reportsrender/templates/adaptive-bootstrap/jquery.sticky-kit.js
reportsrender/templates/adaptive-bootstrap/script.js
reportsrender/templates/adaptive-bootstrap/standalone.html
reportsrender/templates/adaptive-bootstrap/template.css
reportsrender/templates/adaptive-bootstrap/template.html
reportsrender/templates/adaptive-bootstrap/lang/da/language.php
reportsrender/templates/adaptive-bootstrap/lang/en/language.php
reportsrender/templates/adaptive-bootstrap/menu/index.html
reportsrender/templates/adaptive-bootstrap/menu/css/dcaccordion.css
reportsrender/templates/adaptive-bootstrap/menu/css/skins/black.css
reportsrender/templates/adaptive-bootstrap/menu/css/skins/blue.css
reportsrender/templates/adaptive-bootstrap/menu/css/skins/clean.css
reportsrender/templates/adaptive-bootstrap/menu/css/skins/demo.css
reportsrender/templates/adaptive-bootstrap/menu/css/skins/graphite.css
reportsrender/templates/adaptive-bootstrap/menu/css/skins/grey.css
reportsrender/templates/adaptive-bootstrap/menu/css/skins/images/arr_black.gif
reportsrender/templates/adaptive-bootstrap/menu/css/skins/images/arr_white.gif
reportsrender/templates/adaptive-bootstrap/menu/css/skins/images/arrow.png
reportsrender/templates/adaptive-bootstrap/menu/css/skins/images/arrow1.png
reportsrender/templates/adaptive-bootstrap/menu/css/skins/images/arrow2.gif
reportsrender/templates/adaptive-bootstrap/menu/css/skins/images/arrow_black_down.png
reportsrender/templates/adaptive-bootstrap/menu/css/skins/images/arrow_black_right.png
reportsrender/templates/adaptive-bootstrap/menu/css/skins/images/arrow_grey.png
reportsrender-0.3.2.dist-info/entry_points.txt
reportsrender-0.3.2.dist-info/LICENSE
reportsrender-0.3.2.dist-info/WHEEL
reportsrender-0.3.2.dist-info/METADATA
reportsrender-0.3.2.dist-info/RECORD
