Metadata-Version: 2.1
Name: reportsrender
Version: 0.3.2
Summary: Execute and render notebooks as HTML reports. 
Home-page: https://github.com/grst/reportsrender
License: UNKNOWN
Author: Gregor Sturm
Author-email: mail@gregor-sturm.de
Requires-Python: >= 3.6
Classifier: License :: OSI Approved :: MIT License
Classifier: Development Status :: 4 - Beta
Classifier: Intended Audience :: Developers
Classifier: Intended Audience :: Science/Research
Classifier: Programming Language :: Python :: 3
Classifier: Programming Language :: R
Requires-Dist: docopt
Requires-Dist: ipython
Requires-Dist: jupytext>=1.3.0
Requires-Dist: papermill
Requires-Dist: nbconvert
Requires-Dist: ipykernel
Requires-Dist: get_version
Requires-Dist: lxml
Requires-Dist: sphinx>=2 ; extra == "doc"
Requires-Dist: sphinx_autodoc_typehints>=1.8.0 ; extra == "doc"
Requires-Dist: sphinx_rtd_theme>=0.4 ; extra == "doc"
Requires-Dist: pytest ; extra == "test"
Requires-Dist: matplotlib ; extra == "test"
Provides-Extra: doc
Provides-Extra: test
